{
    "orig": {
        "aktenzeichen": "HRB 45513",
        "amtsgericht": "Mainz",
        "event_date": "2015-06-08",
        "event_type": "Veränderungen",
        "federal_state": "rp",
        "full_text": "Amtsgericht Mainz Aktenzeichen: HRB 45513 \nBekannt gemacht am: 08.06.2015 20:05 Uhr\n\n\n\n\nDie in () gesetzten Angaben der Anschrift und des Geschäftszweiges erfolgen ohne Gewähr.\nVeränderungen\n08.06.2015\n\nHRB 45513:Ahmet Gündüz Bau UG (haftungsbeschränkt), Alzey, Am Damm 6, 55232 Alzey.Ist ein Liquidator bestellt, vertritt er allein. Sind mehrere Liquidatoren bestellt, vertreten diese die Gesellschaft gemeinsam. Liquidator: Gündüz, Ahmet, Alzey, *05.06.1967. Die Gesellschaft ist aufgelöst.",
        "gesellschafter": null,
        "inhaber": null,
        "name": "HRB 45513:Ahmet Gündüz Bau UG (haftungsbeschränkt)",
        "notice_id": "181944",
        "posted_on": "2015-06-08",
        "rechtsform": null,
        "sitz": null,
        "url": "https://www.handelsregisterbekanntmachungen.de/en/skripte/hrb.php?rb_id=181944&land_abk=rp"
    },
    "parsed": {
        "flags": [
            {
                "flag": "CompanyClosed",
                "text": "Die\\ Gesellschaft\\ ist\\ aufgel\\öst\\."
            }
        ],
        "officers": [
            {
                "class": "Liquidator",
                "payload": {
                    "city": "Alzey",
                    "dob": "1967-05-06",
                    "lastname": "Gündüz",
                    "name": "Ahmet"
                },
                "text": " Gündüz, Ahmet, Alzey, *05.06.1967."
            }
        ]
    }
}