{
    "orig": {
        "aktenzeichen": "HRA 722188",
        "amtsgericht": "Ulm",
        "event_date": "2010-10-08",
        "event_type": "Neueintragungen",
        "federal_state": "bw",
        "full_text": "Amtsgericht Ulm Aktenzeichen: HRA 722188 \nBekannt gemacht am: 20.10.2010 12:00 Uhr\n\n\n\n\nIn () gesetzte Angaben der Anschrift und des Geschäftszweiges erfolgen ohne Gewähr.\nNeueintragungen\n08.10.2010\n\nAndreas Heck Riedlingen KG, Riedlingen, Industriestraße 2, 88499 Riedlingen.(Der Betrieb eines McDonald´s Restaurants).Kommanditgesellschaft. Geschäftsanschrift: Industriestraße 2, 88499 Riedlingen. Allgemeine Vertretungsregelung: Jeder persönlich haftende Gesellschafter vertritt einzeln. Persönlich haftender Gesellschafter: Heck, Andreas, Blaubeuren, *07.07.1960, mit der Befugnis, im Namen der Gesellschaft mit sich im eigenen Namen oder als Vertreter eines Dritten Rechtsgeschäfte abzuschließen.",
        "gesellschafter": null,
        "inhaber": null,
        "name": "Andreas Heck Riedlingen KG",
        "notice_id": "212662",
        "posted_on": "2010-10-20",
        "rechtsform": null,
        "sitz": null,
        "url": "https://www.handelsregisterbekanntmachungen.de/en/skripte/hrb.php?rb_id=212662&land_abk=bw"
    },
    "parsed": {
        "flags": [
            {
                "flag": "Limited partnership.",
                "text": "Kommanditgesellschaft\\."
            },
            {
                "flag": "with the power to enter into legal transactions on behalf of the Company with itself or as a representative of a third party",
                "text": "mit\\ der\\ Befugnis\\,\\ im\\ Namen\\ der\\ Gesellschaft\\ mit\\ sich\\ im\\ eigenen\\ Namen\\ oder\\ als\\ Vertreter\\ eines\\ Dritten\\ Rechtsgesch\\äfte\\ abzuschlie\\ßen\\."
            }
        ],
        "labels": [
            {
                "label": "address",
                "text": " Industriestraße 2, 88499 Riedlingen."
            }
        ],
        "officers": [
            {
                "class": "PersonalPartner",
                "payload": {
                    "city": "Blaubeuren",
                    "dob": "1960-07-07",
                    "flag": "mit der Befugnis im Namen der Gesellschaft mit sich im eigenen Namen oder als Vertreter eines Dritten Rechtsgeschäfte abzuschließen",
                    "lastname": "Heck",
                    "name": "Andreas"
                },
                "text": " Heck, Andreas, Blaubeuren, *07.07.1960, mit der Befugnis, im Namen der Gesellschaft mit sich im eigenen Namen oder als Vertreter eines Dritten Rechtsgeschäfte abzuschließen."
            }
        ]
    }
}