{
    "orig": {
        "aktenzeichen": "hrb 98360",
        "amtsgericht": "frankfurt am main",
        "event_date": "2014-01-14",
        "event_type": "neueintragungen",
        "federal_state": "he",
        "full_text": "amtsgericht frankfurt am main aktenzeichen: hrb 98360   \nbekannt gemacht am: 20.01.2014 12:00 uhr\n\n\n\n\nveröffentlichungen des amtsgerichts frankfurt am main\r\r\rin () gesetzte angaben der anschrift und des geschäftszweiges erfolgen ohne gewähr.\nneueintragungen\n14.01.2014\n\nwintech europe gmbh, frankfurt am main, berner straße 107, 60437 frankfurt am main. gesellschaft mit beschränkter haftung. gesellschaftsvertrag vom 28.01.2011 die gesellschafterversammlung vom 05.11.2013 hat die änderung des gesellschaftsvertrages in § 1 (sitz) und mit ihr die sitzverlegung von schwalbach am taunus (bisher amtsgericht königstein im taunus hrb 7889) nach frankfurt am main beschlossen. geschäftsanschrift: berner straße 107, 60437 frankfurt am main. gegenstand: groß- und einzelhandel. im- und export von folien und sonnenschutzbeschichtungen, insbesondere für den europäischen markt. stammkapital: 25.000,00 eur. allgemeine vertretungsregelung: ist nur ein geschäftsführer bestellt, so vertritt er die gesellschaft allein. sind mehrere geschäftsführer bestellt, so wird die gesellschaft durch zwei geschäftsführer oder durch einen geschäftsführer gemeinsam mit einem prokuristen vertreten. geschäftsführer: ahn, yoo soo, kronberg im taunus, *19.04.1965, einzelvertretungsberechtigt; mit der befugnis, im namen der gesellschaft mit sich im eigenen namen oder als vertreter eines dritten rechtsgeschäfte abzuschließen.",
        "gesellschafter": null,
        "inhaber": null,
        "name": "wintech europe gmbh",
        "notice_id": "365406",
        "posted_on": "2014-01-20",
        "rechtsform": null,
        "sitz": null,
        "url": "https://www.handelsregisterbekanntmachungen.de/en/skripte/hrb.php?rb_id=365406&land_abk=he"
    },
    "parsed": {
        "flags": [
            {
                "flag": "Company with limited liability.",
                "text": "Gesellschaft\\ mit\\ beschr\\änkter\\ Haftung\\."
            },
            {
                "flag": "If only one managing director is appointed, he represents the company alone.",
                "text": "Ist\\ nur\\ ein\\ Gesch\\äftsf\\ührer\\ bestellt\\,\\ so\\ vertritt\\ er\\ die\\ Gesellschaft\\ allein\\."
            },
            {
                "flag": "If several managing directors are appointed, then the company is represented by two managing directors or by a managing director together with an authorized officer.",
                "text": "Sind\\ mehrere\\ Gesch\\äftsf\\ührer\\ bestellt\\,\\ so\\ wird\\ die\\ Gesellschaft\\ durch\\ zwei\\ Gesch\\äftsf\\ührer\\ oder\\ durch\\ einen\\ Gesch\\äftsf\\ührer\\ gemeinsam\\ mit\\ einem\\ Prokuristen\\ vertreten\\."
            },
            {
                "flag": "with the power to enter into legal transactions on behalf of the Company with itself or as a representative of a third party",
                "text": "mit\\ der\\ Befugnis\\,\\ im\\ Namen\\ der\\ Gesellschaft\\ mit\\ sich\\ im\\ eigenen\\ Namen\\ oder\\ als\\ Vertreter\\ eines\\ Dritten\\ Rechtsgesch\\äfte\\ abzuschlie\\ßen\\."
            }
        ],
        "labels": [
            {
                "label": "address",
                "text": " berner straße 107, 60437 frankfurt am main."
            }
        ],
        "officers": [
            {
                "class": "ManagingDirector",
                "payload": {
                    "city": "kronberg im taunus",
                    "dob": "1965-04-19",
                    "flag": "sole representation",
                    "lastname": "ahn",
                    "name": "yoo soo"
                },
                "text": " ahn, yoo soo, kronberg im taunus, *19.04.1965, einzelvertretungsberechtigt"
            }
        ]
    }
}