{
    "orig": {
        "aktenzeichen": "GnR 57",
        "amtsgericht": "Nürnberg",
        "event_date": "2006-08-25",
        "event_type": "Veränderungen",
        "federal_state": "by",
        "full_text": "Amtsgericht Nürnberg Aktenzeichen: GnR 57 \nBekannt gemacht am: 01.09.2006 12:55 Uhr\n\n\n\n\nDie in ( ) gesetzten Angaben der Geschäftsanschrift und des Geschäftszweiges erfolgen ohne Gewähr.\nVeränderungen\n25.08.2006\n\nStraßenverkehrs-Genossenschaft Nordbayern eG, Nürnberg (Wilhelminenstr. 6, 90461 Nürnberg). Bestellt: Vorstand Gockeln, Werner, Schmitten, *26.05.1956. Ausgeschieden: Vorstand Hein, Jan.",
        "gesellschafter": null,
        "inhaber": null,
        "name": "Straßenverkehrs-Genossenschaft Nordbayern eG",
        "notice_id": "117899",
        "posted_on": "2006-09-01",
        "rechtsform": null,
        "sitz": null,
        "url": "https://www.handelsregisterbekanntmachungen.de/en/skripte/hrb.php?rb_id=117899&land_abk=by"
    },
    "parsed": {}
}