{
    "orig": {
        "aktenzeichen": "HRA 3492",
        "amtsgericht": "Bad Homburg",
        "event_date": "2009-02-09",
        "event_type": "Veränderungen",
        "federal_state": "he",
        "full_text": "Amtsgericht Bad Homburg Aktenzeichen: HRA 3492 \nBekannt gemacht am: 12.02.2009 12:00 Uhr\n\n\n\n\nVeröffentlichungen des Amtsgerichts Bad Homburg v.d. Höhe\r\r\rIn () gesetzte Angaben der Anschrift und des Geschäftszweiges erfolgen ohne Gewähr.\nVeränderungen\n09.02.2009\n\nSAB Real Estate GmbH & Co. \"Neunundsiebzigste Wohnpark Rüdnitz\" KG, Bad Homburg v. d. Höhe, Frankfurter Landstra0e 23, 61352 Bad Homburg v. d. Höhe.Geschäftsanschrift: Frankfurter Landstra0e 23, 61352 Bad Homburg v. d. Höhe. Personenbezogene Daten von Amts wegen berichtigt, nun: Persönlich haftende Gesellschafterin: SAB Real Estate GmbH, Bad Homburg v. d. Höhe (Amtsgericht Bad Homburg v. d. Höhe HRB 10114).",
        "gesellschafter": null,
        "inhaber": null,
        "name": "SAB Real Estate GmbH & Co. \"Neunundsiebzigste Wohnpark Rüdnitz\" KG",
        "notice_id": "120429",
        "posted_on": "2009-02-12",
        "rechtsform": null,
        "sitz": null,
        "url": "https://www.handelsregisterbekanntmachungen.de/en/skripte/hrb.php?rb_id=120429&land_abk=he"
    },
    "parsed": {
        "labels": [
            {
                "label": "address",
                "text": " Frankfurter Landstra0e 23, 61352 Bad Homburg v. d. Höhe."
            }
        ]
    }
}