{
    "orig": {
        "aktenzeichen": "HRB 4562",
        "amtsgericht": "Hamm",
        "event_date": "2017-04-04",
        "event_type": "Löschungen",
        "federal_state": "nw",
        "full_text": "Amtsgericht Hamm Aktenzeichen: HRB 4562 \nBekannt gemacht am: 04.04.2017 20:01 Uhr\n\n\n\n\nIn () gesetzte Angaben der Anschrift und des Geschäftszweiges erfolgen ohne Gewähr.\nLöschungen\n04.04.2017\n\nHRB 4562: HD Lindemann Kamen Verwaltungsgesellschaft mbH, Kamen, Buschweg 7, 59174 Kamen. Die Liquidation ist beendet. Die Firma ist erloschen.",
        "gesellschafter": null,
        "inhaber": null,
        "name": "HRB 4562: HD Lindemann Kamen Verwaltungsgesellschaft mbH",
        "notice_id": "1397798",
        "posted_on": "2017-04-04",
        "rechtsform": null,
        "sitz": null,
        "url": "https://www.handelsregisterbekanntmachungen.de/en/skripte/hrb.php?rb_id=1397798&land_abk=nw"
    },
    "parsed": {}
}