{
    "orig": {
        "aktenzeichen": "HRB 81273",
        "amtsgericht": "Hamburg",
        "event_date": "2015-03-27",
        "event_type": "Löschungen",
        "federal_state": "hh",
        "full_text": "Amtsgericht Hamburg Aktenzeichen: HRB 81273 \nBekannt gemacht am: 27.03.2015 11:07 Uhr\n\n\n\n\nIn () gesetzte Angaben der Anschrift und des Geschäftszweiges erfolgen ohne Gewähr.\nLöschungen\n27.03.2015\n\nHRB 81273:PhonoNet-Media GmbH, Hamburg, Bei der Pulvermühle 7 a, 22453 Hamburg.Die Liquidation ist beendet. Die Firma ist erloschen.",
        "gesellschafter": null,
        "inhaber": null,
        "name": "HRB 81273:PhonoNet-Media GmbH",
        "notice_id": "261975",
        "posted_on": "2015-03-27",
        "rechtsform": null,
        "sitz": null,
        "url": "https://www.handelsregisterbekanntmachungen.de/en/skripte/hrb.php?rb_id=261975&land_abk=hh"
    },
    "parsed": {}
}