{
    "orig": {
        "aktenzeichen": "HRB 595",
        "amtsgericht": "Weiden i. d. OPf (Weiden)",
        "event_date": "2009-01-30",
        "event_type": "Veränderungen",
        "federal_state": "by",
        "full_text": "Amtsgericht Weiden i. d. OPf (Weiden) Aktenzeichen: HRB 595 \nBekannt gemacht am: 10.02.2009 12:00 Uhr\n\n\n\n\nIn ( ) gesetzte Angaben der Anschrift und des Geschäftszweiges erfolgen ohne Gewähr.\nVeränderungen\n30.01.2009\n\nB & E Aktuell Polstermöbel GmbH, Weiden i.d.OPf., Sonnenstraße 31, 92709 Moosbach.Geschäftsanschrift: Sonnenstraße 31, 92709 Moosbach. Ist nur ein Liquidator bestellt, so vertritt er die Gesellschaft allein. Sind mehrere Liquidatoren bestellt, so wird die Gesellschaft durch die Liquidatoren gemeinschaftlich vertreten. Vertretungsbefugnis geändert, nun: Liquidator: Enders, Peter, Moosbach, *24.09.1947. Die Gesellschaft ist aufgelöst.",
        "gesellschafter": null,
        "inhaber": null,
        "name": "B & E Aktuell Polstermöbel GmbH",
        "notice_id": "301688",
        "posted_on": "2009-02-10",
        "rechtsform": null,
        "sitz": null,
        "url": "https://www.handelsregisterbekanntmachungen.de/en/skripte/hrb.php?rb_id=301688&land_abk=by"
    },
    "parsed": {
        "flags": [
            {
                "flag": "ignore_for_now",
                "text": "Die\\ Gesellschaft\\ ist\\ aufgel\\öst\\."
            }
        ],
        "labels": [
            {
                "label": "address",
                "text": " Sonnenstraße 31, 92709 Moosbach."
            }
        ],
        "officers": [
            {
                "class": "Liquidator",
                "payload": {
                    "city": "Moosbach",
                    "dob": "1947-09-24",
                    "lastname": ": Enders",
                    "name": "Peter"
                },
                "text": ": Enders, Peter, Moosbach, *24.09.1947."
            }
        ]
    }
}