{
    "orig": {
        "aktenzeichen": "HRB 42356",
        "amtsgericht": "Offenbach am Main",
        "event_date": "2013-07-19",
        "event_type": "Veränderungen",
        "federal_state": "he",
        "full_text": "Amtsgericht Offenbach am Main Aktenzeichen: HRB 42356   \nBekannt gemacht am: 22.07.2013 12:00 Uhr\n\n\n\n\nVeröffentlichungen des Amtsgerichts Offenbach am Main\r\r\rIn () gesetzte Angaben der Anschrift und des Geschäftszweiges erfolgen ohne Gewähr.\nVeränderungen\n19.07.2013\n\nGerstner & Preuß Verwaltungsgesellschaft mbH, Mühlheim am Main, Spessartstraße 2, 63165 Mühlheim am Main. Die Gesellschafterversammlung vom 10.06.2013 hat eine Änderung des Gesellschaftsvertrages in § 1 Ziffer 1 (Firma) beschlossen. Neue Firma: B.P. Verwaltungsgesellschaft mbH. Geschäftsanschrift: Spessartstraße 2, 63165 Mühlheim am Main. Nicht mehr Geschäftsführerin: Gerstner, Felicitas, Offenbach am Main, *10.11.1952. Geändert, nun: Geschäftsführerin: Preuß, Bianca, Dannenberg, *07.12.1954, einzelvertretungsberechtigt; mit der Befugnis, im Namen der Gesellschaft mit sich im eigenen Namen oder als Vertreter eines Dritten Rechtsgeschäfte abzuschließen.",
        "gesellschafter": null,
        "inhaber": null,
        "name": "Gerstner & Preuß Verwaltungsgesellschaft mbH",
        "notice_id": "340725",
        "posted_on": "2013-07-22",
        "rechtsform": null,
        "sitz": null,
        "url": "https://www.handelsregisterbekanntmachungen.de/en/skripte/hrb.php?rb_id=340725&land_abk=he"
    },
    "parsed": {
        "flags": [
            {
                "flag": "with the power to enter into legal transactions on behalf of the Company with itself or as a representative of a third party",
                "text": "mit\\ der\\ Befugnis\\,\\ im\\ Namen\\ der\\ Gesellschaft\\ mit\\ sich\\ im\\ eigenen\\ Namen\\ oder\\ als\\ Vertreter\\ eines\\ Dritten\\ Rechtsgesch\\äfte\\ abzuschlie\\ßen\\."
            }
        ],
        "labels": [
            {
                "label": "address",
                "text": " Spessartstraße 2, 63165 Mühlheim am Main."
            }
        ],
        "officers": [
            {
                "class": "DismissedManagingDirector",
                "payload": {
                    "city": "Offenbach am Main",
                    "dismissed": true,
                    "dob": "1952-10-11",
                    "lastname": "Gerstner",
                    "name": "Felicitas"
                },
                "text": " Gerstner, Felicitas, Offenbach am Main, *10.11.1952."
            },
            {
                "class": "ManagingDirector",
                "payload": {
                    "city": "Dannenberg",
                    "dob": "1954-07-12",
                    "flag": "sole representation",
                    "lastname": "Preuß",
                    "name": "Bianca"
                },
                "text": " Preuß, Bianca, Dannenberg, *07.12.1954, einzelvertretungsberechtigt"
            }
        ]
    }
}