{
    "orig": {
        "aktenzeichen": "HRA 5255 HL",
        "amtsgericht": "Lübeck",
        "event_date": "2008-08-21",
        "event_type": "Veränderungen",
        "federal_state": "sh",
        "full_text": "Amtsgericht Lübeck Aktenzeichen: HRA 5255 HL \nBekannt gemacht am: 28.08.2008 22:00 Uhr\n\n\n\n\nFür die Angaben in (), die den Unternehmensgegenstand und die Anschrift betreffen, keine Gewähr. In das Handelsregister ist folgendes eingetragen worden.\nVeränderungen\n21.08.2008\n\nBruhn & Bruhn OHG, Fehmarn(Vadersdorf Nr. 3, 23769  Fehmarn OT Vadersdorf). Name der Firma neu: Bruhn & Bruhn Inh. Marc Bruhn e. K. Inhaber: Nicht mehr persönlich haftender Gesellschafter: 2. Bruhn, Hans-Peter; Änderung zu Nr. 1: Inhaber:; Bruhn, Marc, *22.03.1974, Fehmarn. Rechtsform: nunmehr: Einzelunternehmen; Geschäft und Firma sind auf Bruhn, Marc übergegangen. Die Firma ist geändert. Rechtsverhaeltnis: Die Gesellschaft ist aufgelöst..",
        "gesellschafter": null,
        "inhaber": null,
        "name": "Bruhn & Bruhn OHG",
        "notice_id": "40290",
        "posted_on": "2008-08-28",
        "rechtsform": null,
        "sitz": null,
        "url": "https://www.handelsregisterbekanntmachungen.de/en/skripte/hrb.php?rb_id=40290&land_abk=sh"
    },
    "parsed": {
        "flags": [
            {
                "flag": "ignore_for_now",
                "text": "Die\\ Gesellschaft\\ ist\\ aufgel\\öst\\."
            }
        ],
        "officers": [
            {
                "class": "PersonalPartner",
                "payload": {
                    "lastname": "Bruhn",
                    "name": "Hans-Peter"
                },
                "text": " Bruhn, Hans-Peter"
            },
            {
                "class": "Owner",
                "payload": {
                    "city": "Fehmarn",
                    "dob": "1974-03-22",
                    "lastname": "Bruhn",
                    "name": "Marc"
                },
                "text": " Bruhn, Marc, *22.03.1974, Fehmarn."
            }
        ]
    }
}