{
    "orig": {
        "aktenzeichen": "HRB 332879",
        "amtsgericht": "Mannheim",
        "event_date": "2015-02-16",
        "event_type": "Veränderungen",
        "federal_state": "bw",
        "full_text": "Amtsgericht Mannheim Aktenzeichen: HRB 332879 \nBekannt gemacht am: 16.02.2015 10:04 Uhr\n\n\n\n\nIn () gesetzte Angaben der Anschrift und des Geschäftszweiges erfolgen ohne Gewähr:\nVeränderungen\n16.02.2015\n\nHRB 332879:Bierther GmbH, Heidelberg, Tullastr. 13, 69126 Heidelberg.Nicht mehr Geschäftsführer: Weber, Renate, Neckargemünd, *14.05.1947.",
        "gesellschafter": null,
        "inhaber": null,
        "name": "HRB 332879:Bierther GmbH",
        "notice_id": "474307",
        "posted_on": "2015-02-16",
        "rechtsform": null,
        "sitz": null,
        "url": "https://www.handelsregisterbekanntmachungen.de/en/skripte/hrb.php?rb_id=474307&land_abk=bw"
    },
    "parsed": {
        "officers": [
            {
                "class": "DismissedManagingDirector",
                "payload": {
                    "city": "Neckargemünd",
                    "dismissed": true,
                    "dob": "1947-05-14",
                    "lastname": "Weber",
                    "name": "Renate"
                },
                "text": " Weber, Renate, Neckargemünd, *14.05.1947."
            }
        ]
    }
}