{
    "orig": {
        "aktenzeichen": "HRB 37643",
        "amtsgericht": "Köln",
        "event_date": "2009-10-05",
        "event_type": "Löschungen",
        "federal_state": "nw",
        "full_text": "Amtsgericht Köln Aktenzeichen: HRB 37643 \nBekannt gemacht am: 08.10.2009 12:00 Uhr\n\n\n\n\nIn () gesetzte Angaben der Anschrift und des Geschäftszweiges erfolgen ohne Gewähr.\nLöschungen\n05.10.2009\n\nSteinbach Tiefbau GmbH, Wipperfürth, (Dorfstraße 25, 84051 Altheim).Nach Sitzverlegung nunmehr (Amtsgericht Landshut, HRB 7962) Altheim.",
        "gesellschafter": null,
        "inhaber": null,
        "name": "Steinbach Tiefbau GmbH",
        "notice_id": "479499",
        "posted_on": "2009-10-08",
        "rechtsform": null,
        "sitz": null,
        "url": "https://www.handelsregisterbekanntmachungen.de/en/skripte/hrb.php?rb_id=479499&land_abk=nw"
    },
    "parsed": {
        "notices": [
            {
                "court": "Landshut",
                "hrb": "HRB 7962",
                "registration": "successor",
                "text": " nunmehr (Amtsgericht Landshut, HRB 7962) Altheim.",
                "used_regex": "court_regex, hrb"
            }
        ]
    }
}