{
    "orig": {
        "aktenzeichen": "HRB 4518",
        "amtsgericht": "Rostock",
        "event_date": "2013-09-06",
        "event_type": "Veränderungen",
        "federal_state": "mv",
        "full_text": "Amtsgericht Rostock Aktenzeichen: HRB 4518   \nBekannt gemacht am: 11.09.2013 12:00 Uhr\n\n\n\n\nIn ( ) gesetzte Angaben der Anschrift und des Geschäftszweiges erfolgen ohne Gewähr.\nVeränderungen\n06.09.2013\n\nFairplay Entertainment GmbH, Rostock, Kirchenplatz 3, 18119 Rostock. Die Gesellschafterversammlung hat am 22.08.2013 beschlossen, das Stammkapital (DEM 50.000,00) auf Euro umzustellen, es von dann EUR 25.564,59 um EUR 435,41 auf EUR 26.000,00 zu erhöhen und den Gesellschaftsvertrag in § Abs. 1 (Firma), § 3 (Stammkapital), § 12 (Gesellschafterversammlung) zu ändern und § 15 (Gründungsaufwand) ersatzlos zu streichen. Neue Firma: Fairplay Bell Entertainment GmbH. Geschäftsanschrift: Goorstorfer Straße 7, 18182 Bentwisch. 26.000,00 EUR. Nicht mehr Geschäftsführer: Fronzek, Michael, Berlin, *22.07.1944.",
        "gesellschafter": null,
        "inhaber": null,
        "name": "Fairplay Entertainment GmbH",
        "notice_id": "48290",
        "posted_on": "2013-09-11",
        "rechtsform": null,
        "sitz": null,
        "url": "https://www.handelsregisterbekanntmachungen.de/en/skripte/hrb.php?rb_id=48290&land_abk=mv"
    },
    "parsed": {
        "labels": [
            {
                "label": "address",
                "text": " Goorstorfer Straße 7, 18182 Bentwisch."
            }
        ],
        "officers": [
            {
                "class": "DismissedManagingDirector",
                "payload": {
                    "city": "Berlin",
                    "dismissed": true,
                    "dob": "1944-07-22",
                    "lastname": "Fronzek",
                    "name": "Michael"
                },
                "text": " Fronzek, Michael, Berlin, *22.07.1944."
            }
        ]
    }
}