{
    "orig": {
        "aktenzeichen": "HRA 10250",
        "amtsgericht": "Wiesbaden",
        "event_date": "2016-05-03",
        "event_type": "Löschungen",
        "federal_state": "he",
        "full_text": "Amtsgericht Wiesbaden Aktenzeichen: HRA 10250 \nBekannt gemacht am: 03.05.2016 22:03 Uhr\n\n\n\n\nVeröffentlichungen des Amtsgerichts Wiesbaden\n\n\nIn () gesetzte Angaben der Anschrift und des Geschäftszweiges erfolgen ohne Gewähr.\nLöschungen\n03.05.2016\n\nHRA 10250: Hausverwaltung Eveline Boller Inh. Katrin Senger e. K., Wiesbaden, Rheinstraße 38, 65185 Wiesbaden. Mainz. Geschäftsanschrift: Alte Mainzer Straße 3, 55129 Mainz. Die Niederlassung ist nach Mainz (jetzt Amtsgericht Mainz, HRA 42853) verlegt.",
        "gesellschafter": null,
        "inhaber": null,
        "name": "HRA 10250: Hausverwaltung Eveline Boller Inh. Katrin Senger e. K.",
        "notice_id": "485044",
        "posted_on": "2016-05-03",
        "rechtsform": null,
        "sitz": null,
        "url": "https://www.handelsregisterbekanntmachungen.de/en/skripte/hrb.php?rb_id=485044&land_abk=he"
    },
    "parsed": {
        "labels": [
            {
                "label": "address",
                "text": " Alte Mainzer Straße 3, 55129 Mainz."
            }
        ]
    }
}