{
    "orig": {
        "aktenzeichen": "HRA 310536",
        "amtsgericht": "Freiburg",
        "event_date": "2016-01-04",
        "event_type": "Veränderungen",
        "federal_state": "bw",
        "full_text": "Amtsgericht Freiburg Aktenzeichen: HRA 310536 \nBekannt gemacht am: 04.01.2016 13:38 Uhr\n\n\n\n\nIn () gesetzte Angaben der Anschrift und des Geschäftszweiges erfolgen ohne Gewähr:\nVeränderungen\n04.01.2016\n\nHRA 310536: Schimmele KG, Staufen im Breisgau, Großmattenstraße 26, 79219 Staufen im Breisgau. Sitz verlegt; nun: Stegen. Änderung der Geschäftsanschrift: Eichbühl 16, 79252 Stegen.",
        "gesellschafter": null,
        "inhaber": null,
        "name": "HRA 310536: Schimmele KG",
        "notice_id": "526661",
        "posted_on": "2016-01-04",
        "rechtsform": null,
        "sitz": null,
        "url": "https://www.handelsregisterbekanntmachungen.de/en/skripte/hrb.php?rb_id=526661&land_abk=bw"
    },
    "parsed": {
        "labels": [
            {
                "label": "address",
                "text": " Eichbühl 16, 79252 Stegen."
            }
        ]
    }
}