{
    "orig": {
        "aktenzeichen": "HRB 193676",
        "amtsgericht": "München",
        "event_date": "2011-08-19",
        "event_type": "Neueintragungen",
        "federal_state": "by",
        "full_text": "Amtsgericht München Aktenzeichen: HRB 193676   \nBekannt gemacht am: 24.08.2011 12:00 Uhr\n\n\n\n\nIn ( ) gesetzte Angaben der Anschrift und des Geschäftszweiges erfolgen ohne Gewähr.\nNeueintragungen\n19.08.2011\n\nmicroDimensions GmbH, Garching b. München, Landkreis München, Boltzmannstraße 11, 85748 Garching. Gesellschaft mit beschränkter Haftung. Gesellschaftsvertrag vom 04.08.2011. Geschäftsanschrift: Boltzmannstraße 11, 85748 Garching. Gegenstand des Unternehmens: Entwicklung und Herstellung sowie Vermarktung und Vertrieb von Geräten und Systemen zur Bearbeitung, Analyse und Visualisierung von Informationen.; Beratungsdienstleistungen zur Realisierung solcher Geräte und Systeme; Stammkapital: 25.500,00 EUR. Ist nur ein Geschäftsführer bestellt, so vertritt er die Gesellschaft allein. Sind mehrere Geschäftsführer bestellt, so wird die Gesellschaft durch zwei Geschäftsführer oder durch einen Geschäftsführer gemeinsam mit einem Prokuristen vertreten. Geschäftsführer: Dr. Feuerstein, Marco, München, *05.06.1978; Dr. Groher, Martin, München, *05.01.1978; Dr. Heibel, Hauke, München, *09.10.1976, jeweils einzelvertretungsberechtigt.",
        "gesellschafter": null,
        "inhaber": null,
        "name": "microDimensions GmbH",
        "notice_id": "529354",
        "posted_on": "2011-08-24",
        "rechtsform": null,
        "sitz": null,
        "url": "https://www.handelsregisterbekanntmachungen.de/en/skripte/hrb.php?rb_id=529354&land_abk=by"
    },
    "parsed": {
        "flags": [
            {
                "flag": "Company with limited liability.",
                "text": "Gesellschaft\\ mit\\ beschr\\änkter\\ Haftung\\."
            },
            {
                "flag": "If only one managing director is appointed, he represents the company alone.",
                "text": "Ist\\ nur\\ ein\\ Gesch\\äftsf\\ührer\\ bestellt\\,\\ so\\ vertritt\\ er\\ die\\ Gesellschaft\\ allein\\."
            },
            {
                "flag": "If several managing directors are appointed, then the company is represented by two managing directors or by a managing director together with an authorized officer.",
                "text": "Sind\\ mehrere\\ Gesch\\äftsf\\ührer\\ bestellt\\,\\ so\\ wird\\ die\\ Gesellschaft\\ durch\\ zwei\\ Gesch\\äftsf\\ührer\\ oder\\ durch\\ einen\\ Gesch\\äftsf\\ührer\\ gemeinsam\\ mit\\ einem\\ Prokuristen\\ vertreten\\."
            }
        ],
        "labels": [
            {
                "label": "address",
                "text": " Boltzmannstraße 11, 85748 Garching."
            }
        ],
        "officers": [
            {
                "class": "ManagingDirector",
                "payload": {
                    "city": "München",
                    "dob": "1978-05-06",
                    "lastname": "Doctor Feuerstein",
                    "name": "Marco"
                },
                "text": " Doctor Feuerstein, Marco, München, *05.06.1978"
            }
        ]
    }
}