{
    "orig": {
        "aktenzeichen": "HRB 3029",
        "amtsgericht": "Coburg",
        "event_date": "2011-11-21",
        "event_type": "Veränderungen",
        "federal_state": "by",
        "full_text": "Amtsgericht Coburg Aktenzeichen: HRB 3029   \nBekannt gemacht am: 22.11.2011 12:00 Uhr\n\n\n\n\nIn ( ) gesetzte Angaben der Anschrift und des Geschäftszweiges erfolgen ohne Gewähr.\nVeränderungen\n21.11.2011\n\nSoftware Partner Obermain GmbH, Burgkunstadt, Bahnhofstr. 33, 96224 Burgkunstadt. Ausgeschieden: Geschäftsführer: Sell, Stephan, Küps, *19.04.1962.",
        "gesellschafter": null,
        "inhaber": null,
        "name": "Software Partner Obermain GmbH",
        "notice_id": "551619",
        "posted_on": "2011-11-22",
        "rechtsform": null,
        "sitz": null,
        "url": "https://www.handelsregisterbekanntmachungen.de/en/skripte/hrb.php?rb_id=551619&land_abk=by"
    },
    "parsed": {
        "officers": [
            {
                "class": "RetiredManagingDirector",
                "payload": {
                    "city": "Küps",
                    "dismissed": true,
                    "dob": "1962-04-19",
                    "lastname": "Sell",
                    "name": "Stephan"
                },
                "text": " Sell, Stephan, Küps, *19.04.1962."
            }
        ]
    }
}