{
    "orig": {
        "aktenzeichen": "HRA 22023",
        "amtsgericht": "Darmstadt",
        "event_date": "2018-05-04",
        "event_type": "Veränderungen",
        "federal_state": "he",
        "full_text": "Amtsgericht Darmstadt Aktenzeichen: HRA 22023 \nBekannt gemacht am: 04.05.2018 22:00 Uhr\n\n\n\n\nVeröffentlichungen des Amtsgerichts Darmstadt\n\n\nIn () gesetzte Angaben der Anschrift und des Geschäftszweiges erfolgen ohne Gewähr.\nVeränderungen\n04.05.2018\n\nHRA 22023: ODENWALD QUELLE GmbH & Co. KG, Heppenheim (Bergstraße), Ludwigstraße 100, 64646 Heppenheim (Bergstraße). Prokura erloschen: Fechner, Bianca, Mörlenbach, *07.05.1985.",
        "gesellschafter": null,
        "inhaber": null,
        "name": "HRA 22023: ODENWALD QUELLE GmbH & Co. KG",
        "notice_id": "592442",
        "posted_on": "2018-05-04",
        "rechtsform": null,
        "sitz": null,
        "url": "https://www.handelsregisterbekanntmachungen.de/en/skripte/hrb.php?rb_id=592442&land_abk=he"
    },
    "parsed": {
        "officers": [
            {
                "class": "ProcurationCancelled",
                "payload": {
                    "city": "Mörlenbach",
                    "dismissed": true,
                    "dob": "1985-07-05",
                    "lastname": "Fechner",
                    "name": "Bianca"
                },
                "text": " Fechner, Bianca, Mörlenbach, *07.05.1985."
            }
        ]
    }
}