{
    "orig": {
        "aktenzeichen": "HRB 46806",
        "amtsgericht": "Köln",
        "event_date": "2012-02-21",
        "event_type": "Veränderungen",
        "federal_state": "nw",
        "full_text": "Amtsgericht Köln Aktenzeichen: HRB 46806   \nBekannt gemacht am: 22.02.2012 22:00 Uhr\n\n\n\n\nIn () gesetzte Angaben der Anschrift und des Geschäftszweiges erfolgen ohne Gewähr.\nVeränderungen\n21.02.2012\n\no3sis AG, Overath, Olper Str. 33, 51491 Overath. Bestellt als Vorstand: Gallois, Sébastien, München, *24.07.1972, einzelvertretungsberechtigt mit der Befugnis im Namen der Gesellschaft mit sich als Vertreter eines Dritten Rechtsgeschäfte abzuschließen. Nach Berichtigung von Amts wegen: Vorstand: Heymann, Ute, Kauffrau, Much; Rützel, Bernd, Kaufmann, Rösrath, jeweils einzelvertretungsberechtigt mit der Befugnis im Namen der Gesellschaft mit sich als Vertreter eines Dritten Rechtsgeschäfte abzuschließen.",
        "gesellschafter": null,
        "inhaber": null,
        "name": "o3sis AG",
        "notice_id": "767908",
        "posted_on": "2012-02-22",
        "rechtsform": null,
        "sitz": null,
        "url": "https://www.handelsregisterbekanntmachungen.de/en/skripte/hrb.php?rb_id=767908&land_abk=nw"
    },
    "parsed": {}
}