{
    "orig": {
        "aktenzeichen": "HRB 107008",
        "amtsgericht": "Stendal",
        "event_date": "2015-06-12",
        "event_type": "Veränderungen",
        "federal_state": "st",
        "full_text": "Amtsgericht Stendal Aktenzeichen: HRB 107008 \nBekannt gemacht am: 12.06.2015 12:57 Uhr\n\n\n\n\nDie in () gesetzten Angaben der Geschäftsanschrift und des Geschäftszweiges erfolgen ohne Gewähr.\nVeränderungen\n12.06.2015\n\nHRB 107008:Architektur- und Ingenieurbüro \"alt & neu\" GmbH, Wernigerode, Forckestraße 2, 38855 Wernigerode.Ausgeschieden: Geschäftsführer: Vollmer, Sabine, Elbingerode, *08.10.1947.",
        "gesellschafter": null,
        "inhaber": null,
        "name": "HRB 107008:Architektur- und Ingenieurbüro \"alt & neu\" GmbH",
        "notice_id": "83677",
        "posted_on": "2015-06-12",
        "rechtsform": null,
        "sitz": null,
        "url": "https://www.handelsregisterbekanntmachungen.de/en/skripte/hrb.php?rb_id=83677&land_abk=st"
    },
    "parsed": {
        "officers": [
            {
                "class": "RetiredManagingDirector",
                "payload": {
                    "city": "Elbingerode",
                    "dismissed": true,
                    "dob": "1947-08-10",
                    "lastname": "Vollmer",
                    "name": "Sabine"
                },
                "text": " Vollmer, Sabine, Elbingerode, *08.10.1947."
            }
        ]
    }
}