{
    "orig": {
        "aktenzeichen": "HRB 211290",
        "amtsgericht": "Stendal",
        "event_date": "2016-07-06",
        "event_type": "Veränderungen",
        "federal_state": "st",
        "full_text": "Amtsgericht Stendal Aktenzeichen: HRB 211290 \nBekannt gemacht am: 06.07.2016 08:56 Uhr\n\n\n\n\nDie in () gesetzten Angaben der Geschäftsanschrift und des Geschäftszweiges erfolgen ohne Gewähr.\nVeränderungen\n06.07.2016\n\nHRB 211290: Manuli Stretch Deutschland GmbH, Schkopau, Dow Olefinverbund, Valuepark/Bau Z 20, 06258 Schkopau. Geändert, nun: Geschäftsführer: Passera, Corrado, Lodi/Italien / Italien, *04.10.1968, mit der Befugnis, im Namen der Gesellschaft mit sich im eigenen Namen oder als Vertreter eines Dritten Rechtsgeschäfte abzuschließen.",
        "gesellschafter": null,
        "inhaber": null,
        "name": "HRB 211290: Manuli Stretch Deutschland GmbH",
        "notice_id": "93366",
        "posted_on": "2016-07-06",
        "rechtsform": null,
        "sitz": null,
        "url": "https://www.handelsregisterbekanntmachungen.de/en/skripte/hrb.php?rb_id=93366&land_abk=st"
    },
    "parsed": {
        "flags": [
            {
                "flag": "with the power to enter into legal transactions on behalf of the Company with itself or as a representative of a third party",
                "text": "mit\\ der\\ Befugnis\\,\\ im\\ Namen\\ der\\ Gesellschaft\\ mit\\ sich\\ im\\ eigenen\\ Namen\\ oder\\ als\\ Vertreter\\ eines\\ Dritten\\ Rechtsgesch\\äfte\\ abzuschlie\\ßen\\."
            }
        ],
        "officers": [
            {
                "class": "ManagingDirector",
                "payload": {
                    "city": "Lodi/Italien / Italien",
                    "dob": "1968-04-10",
                    "flag": "mit der Befugnis im Namen der Gesellschaft mit sich im eigenen Namen oder als Vertreter eines Dritten Rechtsgeschäfte abzuschließen",
                    "lastname": "Passera",
                    "name": "Corrado"
                },
                "text": " Passera, Corrado, Lodi/Italien / Italien, *04.10.1968, mit der Befugnis, im Namen der Gesellschaft mit sich im eigenen Namen oder als Vertreter eines Dritten Rechtsgeschäfte abzuschließen."
            }
        ]
    }
}