{
    "orig": {
        "aktenzeichen": "HRB 201113",
        "amtsgericht": "Jena",
        "event_date": "2016-06-10",
        "event_type": "Veränderungen",
        "federal_state": "th",
        "full_text": "Amtsgericht Jena Aktenzeichen: HRB 201113 \nBekannt gemacht am: 10.06.2016 12:30 Uhr\n\n\n\n\nDie in () gesetzten Angaben der Geschäftsanschrift und des Unternehmensgegenstandes erfolgen ohne Gewähr.\nVeränderungen\n10.06.2016\n\nHRB 201113: Arno Kolbe & Partner Gesellschaft mit beschränkter Haftung Klempnereibedarf, Gera, Ronneburger Str. 57, 07546 Gera. Die Gesellschafterversammlung vom 02.06.2016 hat den Gesellschaftsvertrag neu gefasst. Dabei wurde insbesondere geändert: Gegenstand. Neuer Gegenstand: ist der Handel und die Herstellung von Klempnereierzeugnissen aller Art. Personenbezogene Daten von Amts wegen geändert, nun: Geschäftsführer: Kolbe, Arno, Knau/Thüringen, *10.08.1955, einzelvertretungsberechtigt; mit der Befugnis, im Namen der Gesellschaft mit sich im eigenen Namen oder als Vertreter eines Dritten Rechtsgeschäfte abzuschließen.",
        "gesellschafter": null,
        "inhaber": null,
        "name": "HRB 201113: Arno Kolbe & Partner Gesellschaft mit beschränkter Haftung Klempnereibedarf",
        "notice_id": "96488",
        "posted_on": "2016-06-10",
        "rechtsform": null,
        "sitz": null,
        "url": "https://www.handelsregisterbekanntmachungen.de/en/skripte/hrb.php?rb_id=96488&land_abk=th"
    },
    "parsed": {
        "flags": [
            {
                "flag": "with the power to enter into legal transactions on behalf of the Company with itself or as a representative of a third party",
                "text": "mit\\ der\\ Befugnis\\,\\ im\\ Namen\\ der\\ Gesellschaft\\ mit\\ sich\\ im\\ eigenen\\ Namen\\ oder\\ als\\ Vertreter\\ eines\\ Dritten\\ Rechtsgesch\\äfte\\ abzuschlie\\ßen\\."
            }
        ],
        "officers": [
            {
                "class": "ManagingDirector",
                "payload": {
                    "city": "Knau/Thüringen",
                    "dob": "1955-10-08",
                    "flag": "sole representation",
                    "lastname": "Kolbe",
                    "name": "Arno"
                },
                "text": " Kolbe, Arno, Knau/Thüringen, *10.08.1955, einzelvertretungsberechtigt"
            }
        ]
    }
}